{"data":{"priceList":{"frontmatter":{"title":"Услуги & Цены","description":"Наши цены вас приятно удивят, а широкий спектр услуг и индивидуальный подход к каждому клиенту не оставят равнодушным.","button":"Все услуги и цены"}},"pricesM":{"edges":[{"node":{"frontmatter":{"id":"1","item":"Мужская Стрижка","price":"30 р."}}},{"node":{"frontmatter":{"id":"3","item":"Стрижка Машинкой","price":"20 р."}}},{"node":{"frontmatter":{"id":"4","item":"Укладка","price":"20 р."}}},{"node":{"frontmatter":{"id":"2","item":"Детская Стрижка (до 10 лет)","price":"20 р."}}},{"node":{"frontmatter":{"id":"5","item":"Пробор/Окантовка","price":"10 р."}}},{"node":{"frontmatter":{"id":"6","item":"Моделирование Бороды","price":"20 р."}}},{"node":{"frontmatter":{"id":"7","item":"Окрашивание (тонирование) волос","price":"от 30 р."}}},{"node":{"frontmatter":{"id":"8","item":"Королевское Бритьё","price":"40 р."}}},{"node":{"frontmatter":{"id":"9","item":"Тонировка Бороды","price":"30 р."}}}]},"pricesW":{"edges":[{"node":{"frontmatter":{"id":"2","item":"Окрашивание волос","price":"от 60 р."}}},{"node":{"frontmatter":{"id":"1","item":"Женская стрижка","price":"от 40 р."}}},{"node":{"frontmatter":{"id":"3","item":"Укладка волос + Mытье головы","price":"от 20 р."}}},{"node":{"frontmatter":{"id":"4","item":"Вечерняя укладка","price":"от 50 р."}}},{"node":{"frontmatter":{"id":"6","item":"Эковосстановление O'right","price":"95 р."}}},{"node":{"frontmatter":{"id":"5","item":"Локоны","price":"55 р."}}},{"node":{"frontmatter":{"id":"7","item":"Стрижка челки","price":"10 р."}}},{"node":{"frontmatter":{"id":"8","item":"Комплекс стрижка \"Семья\" (3 чел)","price":"90 р."}}},{"node":{"frontmatter":{"id":"9","item":"Рисунок хной (махенди)","price":"от 10 р."}}}]}}}